{"assets/.DS_Store":["assets/.DS_Store","assets/m1_1_chon_manh_ghep/.DS_Store","assets/m1_5_ratio/.DS_Store","assets/m1_2_order_rotate/.DS_Store","assets/sound/.DS_Store","assets/thumbnails/.DS_Store"],"assets/MathKids.png":["assets/MathKids.png"],"assets/lose1.gif":["assets/lose1.gif"],"assets/lose2.gif":["assets/lose2.gif"],"assets/lose3.gif":["assets/lose3.gif"],"assets/m1_1_chon_manh_ghep/.DS_Store":["assets/m1_1_chon_manh_ghep/.DS_Store"],"assets/m1_1_chon_manh_ghep/Answer.png":["assets/m1_1_chon_manh_ghep/Answer.png"],"assets/m1_1_chon_manh_ghep/DeBai.png":["assets/m1_1_chon_manh_ghep/DeBai.png"],"assets/m1_1_chon_manh_ghep/Option1.png":["assets/m1_1_chon_manh_ghep/Option1.png"],"assets/m1_1_chon_manh_ghep/Option2.png":["assets/m1_1_chon_manh_ghep/Option2.png"],"assets/m1_1_chon_manh_ghep/Option3.png":["assets/m1_1_chon_manh_ghep/Option3.png"],"assets/m1_1_chon_manh_ghep/Option4.png":["assets/m1_1_chon_manh_ghep/Option4.png"],"assets/m1_1_chon_manh_ghep/answer_2.png":["assets/m1_1_chon_manh_ghep/answer_2.png"],"assets/m1_1_chon_manh_ghep/option2_1.png":["assets/m1_1_chon_manh_ghep/option2_1.png"],"assets/m1_1_chon_manh_ghep/option2_2.png":["assets/m1_1_chon_manh_ghep/option2_2.png"],"assets/m1_1_chon_manh_ghep/option2_3.png":["assets/m1_1_chon_manh_ghep/option2_3.png"],"assets/m1_1_chon_manh_ghep/option2_4.png":["assets/m1_1_chon_manh_ghep/option2_4.png"],"assets/m1_1_chon_manh_ghep/question2.png":["assets/m1_1_chon_manh_ghep/question2.png"],"assets/m1_2_order_rotate/.DS_Store":["assets/m1_2_order_rotate/.DS_Store"],"assets/m1_2_order_rotate/1.jpg":["assets/m1_2_order_rotate/1.jpg"],"assets/m1_2_order_rotate/2.jpg":["assets/m1_2_order_rotate/2.jpg"],"assets/m1_2_order_rotate/3.jpg":["assets/m1_2_order_rotate/3.jpg"],"assets/m1_2_order_rotate/4.jpg":["assets/m1_2_order_rotate/4.jpg"],"assets/m1_2_order_rotate/Presentation1.pptx":["assets/m1_2_order_rotate/Presentation1.pptx"],"assets/m1_3_memory/animals.pptx":["assets/m1_3_memory/animals.pptx"],"assets/m1_3_memory/card_back.jpg":["assets/m1_3_memory/card_back.jpg"],"assets/m1_3_memory/elephant.jpg":["assets/m1_3_memory/elephant.jpg"],"assets/m1_3_memory/hippo.jpg":["assets/m1_3_memory/hippo.jpg"],"assets/m1_3_memory/lion.jpg":["assets/m1_3_memory/lion.jpg"],"assets/m1_3_memory/monkey.jpg":["assets/m1_3_memory/monkey.jpg"],"assets/m1_3_memory/penguin.jpg":["assets/m1_3_memory/penguin.jpg"],"assets/m1_3_memory/pig.jpg":["assets/m1_3_memory/pig.jpg"],"assets/m1_3_memory/rabbit.jpg":["assets/m1_3_memory/rabbit.jpg"],"assets/m1_3_memory/zebra.jpg":["assets/m1_3_memory/zebra.jpg"],"assets/m1_4_count_triangles/1.png":["assets/m1_4_count_triangles/1.png"],"assets/m1_4_count_triangles/1_blue.png":["assets/m1_4_count_triangles/1_blue.png"],"assets/m1_4_count_triangles/2.png":["assets/m1_4_count_triangles/2.png"],"assets/m1_4_count_triangles/2_blue.png":["assets/m1_4_count_triangles/2_blue.png"],"assets/m1_4_count_triangles/3.png":["assets/m1_4_count_triangles/3.png"],"assets/m1_4_count_triangles/3_blue.png":["assets/m1_4_count_triangles/3_blue.png"],"assets/m1_4_count_triangles/5.png":["assets/m1_4_count_triangles/5.png"],"assets/m1_4_count_triangles/6.png":["assets/m1_4_count_triangles/6.png"],"assets/m1_4_count_triangles/7.png":["assets/m1_4_count_triangles/7.png"],"assets/m1_4_count_triangles/8.png":["assets/m1_4_count_triangles/8.png"],"assets/m1_4_count_triangles/Presentation1%20%5BAutosaved%5D.pptx":["assets/m1_4_count_triangles/Presentation1%20%5BAutosaved%5D.pptx"],"assets/m1_4_count_triangles/a.png":["assets/m1_4_count_triangles/a.png"],"assets/m1_4_count_triangles/a_blue.png":["assets/m1_4_count_triangles/a_blue.png"],"assets/m1_4_count_triangles/b.png":["assets/m1_4_count_triangles/b.png"],"assets/m1_4_count_triangles/b_blue.png":["assets/m1_4_count_triangles/b_blue.png"],"assets/m1_4_count_triangles/c.png":["assets/m1_4_count_triangles/c.png"],"assets/m1_4_count_triangles/c_blue.png":["assets/m1_4_count_triangles/c_blue.png"],"assets/m1_4_count_triangles/d.png":["assets/m1_4_count_triangles/d.png"],"assets/m1_4_count_triangles/d_blue.png":["assets/m1_4_count_triangles/d_blue.png"],"assets/m1_4_count_triangles/square1.png":["assets/m1_4_count_triangles/square1.png"],"assets/m1_4_count_triangles/square1_blue.png":["assets/m1_4_count_triangles/square1_blue.png"],"assets/m1_5_ratio/.DS_Store":["assets/m1_5_ratio/.DS_Store"],"assets/m1_5_ratio/cat.png":["assets/m1_5_ratio/cat.png"],"assets/m1_5_ratio/coin.png":["assets/m1_5_ratio/coin.png"],"assets/m1_5_ratio/juice.png":["assets/m1_5_ratio/juice.png"],"assets/m1_5_ratio/kitten.png":["assets/m1_5_ratio/kitten.png"],"assets/m1_5_ratio/strawberry.png":["assets/m1_5_ratio/strawberry.png"],"assets/m1_5_ratio/yogurt.png":["assets/m1_5_ratio/yogurt.png"],"assets/m1_6_pattern/%E2%80%94Pngtree%E2%80%94set%20of%20fruits%20icon%20in_5332166.png":["assets/m1_6_pattern/%E2%80%94Pngtree%E2%80%94set%20of%20fruits%20icon%20in_5332166.png"],"assets/m1_6_pattern/cam.png":["assets/m1_6_pattern/cam.png"],"assets/m1_6_pattern/chuoi.png":["assets/m1_6_pattern/chuoi.png"],"assets/m1_6_pattern/duahau.png":["assets/m1_6_pattern/duahau.png"],"assets/m1_6_pattern/khe.png":["assets/m1_6_pattern/khe.png"],"assets/m1_6_pattern/mangcut.png":["assets/m1_6_pattern/mangcut.png"],"assets/m1_6_pattern/vai.png":["assets/m1_6_pattern/vai.png"],"assets/sound/.DS_Store":["assets/sound/.DS_Store"],"assets/sound/cheer.mp3":["assets/sound/cheer.mp3"],"assets/sound/correct1.mp3":["assets/sound/correct1.mp3"],"assets/sound/correct2.mp3":["assets/sound/correct2.mp3"],"assets/sound/correct3.mp3":["assets/sound/correct3.mp3"],"assets/sound/ping.mp3":["assets/sound/ping.mp3"],"assets/sound/wrong1.mp3":["assets/sound/wrong1.mp3"],"assets/sound/wrong2.mp3":["assets/sound/wrong2.mp3"],"assets/sound/wrong3.mp3":["assets/sound/wrong3.mp3"],"assets/thumbnails/.DS_Store":["assets/thumbnails/.DS_Store"],"assets/thumbnails/1_1.png":["assets/thumbnails/1_1.png"],"assets/thumbnails/1_10.png":["assets/thumbnails/1_10.png"],"assets/thumbnails/1_11.png":["assets/thumbnails/1_11.png"],"assets/thumbnails/1_12.png":["assets/thumbnails/1_12.png"],"assets/thumbnails/1_2.png":["assets/thumbnails/1_2.png"],"assets/thumbnails/1_3.png":["assets/thumbnails/1_3.png"],"assets/thumbnails/1_4a.png":["assets/thumbnails/1_4a.png"],"assets/thumbnails/1_4b.png":["assets/thumbnails/1_4b.png"],"assets/thumbnails/1_5a1.png":["assets/thumbnails/1_5a1.png"],"assets/thumbnails/1_5a2.png":["assets/thumbnails/1_5a2.png"],"assets/thumbnails/1_5b1.png":["assets/thumbnails/1_5b1.png"],"assets/thumbnails/1_5b2.png":["assets/thumbnails/1_5b2.png"],"assets/thumbnails/1_5c1.png":["assets/thumbnails/1_5c1.png"],"assets/thumbnails/1_5c2.png":["assets/thumbnails/1_5c2.png"],"assets/thumbnails/1_6.png":["assets/thumbnails/1_6.png"],"assets/thumbnails/1_7.png":["assets/thumbnails/1_7.png"],"assets/thumbnails/1_8.png":["assets/thumbnails/1_8.png"],"assets/thumbnails/1_9.png":["assets/thumbnails/1_9.png"],"assets/win1.gif":["assets/win1.gif"],"assets/win2.gif":["assets/win2.gif"],"assets/win3.gif":["assets/win3.gif"]}